setup.py
ifttt/__init__.py
ifttt/config.py
ifttt/core.py
ifttt.egg-info/PKG-INFO
ifttt.egg-info/SOURCES.txt
ifttt.egg-info/dependency_links.txt
ifttt.egg-info/requires.txt
ifttt.egg-info/top_level.txt