Metadata-Version: 1.1
Name: ifttt
Version: 0.2.9
Summary: A Pythonic interface for building IFTTT plugins routed over email.
Home-page: https://github.com/newslynx/ifttt
Author: Brian Abelson
Author-email: brian@newslynx.org
License: MIT
Keywords: email,ifttt
Platform: UNKNOWN
Classifier: Development Status :: 3 - Alpha
Classifier: Topic :: Communications :: Email
Classifier: License :: OSI Approved :: MIT License
